{"extension":".bundle","saveBundleName":false,"dirs":["Assets/ZRes/Assembly","Assets/ZRes/Config","Assets/ZRes/UI/Prefab"],"assets":[{"name":"HotAssembly.bytes","bundle":0,"dir":0,"deps":[],"addressMode":2},{"name":"Data_DeviceInfo.bytes","bundle":1,"dir":1,"deps":[],"addressMode":2},{"name":"Data_Test.bytes","bundle":2,"dir":1,"deps":[],"addressMode":2},{"name":"Data_UIConfig.bytes","bundle":3,"dir":1,"deps":[],"addressMode":2},{"name":"UIHotUpdateRes.prefab","bundle":4,"dir":2,"deps":[],"addressMode":2},{"name":"UIMessageBox.prefab","bundle":5,"dir":2,"deps":[],"addressMode":2},{"name":"UITest.prefab","bundle":6,"dir":2,"deps":[],"addressMode":2}],"bundles":[{"name":"assembly_hotassembly_bytes.bundle","hash":"05a60141f7261d90ed9f9864b561c497","size":11966,"deps":[]},{"name":"config_data_deviceinfo_bytes.bundle","hash":"e34804333d00380bb2c6911a0acaf0b8","size":2244,"deps":[]},{"name":"config_data_test_bytes.bundle","hash":"0cc3a15ed15c3e8dbfb358875f89ad6e","size":1431,"deps":[]},{"name":"config_data_uiconfig_bytes.bundle","hash":"37648ec164575802d7709f7996b2f39e","size":1274,"deps":[]},{"name":"prefab_uihotupdateres_prefab.bundle","hash":"3461507ef8fab1d977c21f795587c4d9","size":629551,"deps":[]},{"name":"prefab_uimessagebox_prefab.bundle","hash":"b7c11315157b36528bc70c0b8c8e4b21","size":632331,"deps":[]},{"name":"prefab_uitest_prefab.bundle","hash":"46d6ff4bb384af4fbbf58ffc422ad8a4","size":625904,"deps":[]}]}